venvalid/__init__.py
venvalid/core.py
venvalid/dotenv.py
venvalid/errors.py
venvalid/types.py
venvalid/utils.py
venvalid/utils_errors.py
venvalid/validator.py
venvalid-0.3.0.dist-info/licenses/LICENSE
venvalid-0.3.0.dist-info/METADATA
venvalid-0.3.0.dist-info/WHEEL
venvalid-0.3.0.dist-info/top_level.txt
venvalid-0.3.0.dist-info/RECORD
