Metadata-Version: 2.4
Name: venvalid
Version: 0.3.0
Summary: A minimal and developer-friendly environment variable validator for Python, inspired by envalid.
Author-email: PinnLabs <it@pinnlabs.online>
License-Expression: MIT
Project-URL: Homepage, https://github.com/pinnlabs/venvalid
Project-URL: Repository, https://github.com/pinnlabs/venvalid
Keywords: env,dotenv,validation,envalid,configuration
Classifier: Programming Language :: Python :: 3
Classifier: Operating System :: OS Independent
Requires-Python: >=3.8
License-File: LICENSE
Requires-Dist: build>=1.2.2.post1
Requires-Dist: pytest>=8.3.5
Requires-Dist: rich>=14.1.0
Requires-Dist: twine>=6.1.0
Provides-Extra: dev
Requires-Dist: pytest; extra == "dev"
Dynamic: license-file
